waterstand.py
waterstand-1.4.2.dist-info/METADATA
waterstand-1.4.2.dist-info/WHEEL
waterstand-1.4.2.dist-info/licenses/LICENSE
waterstand-1.4.2.dist-info/RECORD
