Metadata-Version: 2.4
Name: waterstand
Version: 1.4.2
Summary: package voor ophalen waterstand
Project-URL: Homepage, https://github.com/vdriet/waterstand
Project-URL: Issues, https://github.com/vdriet/waterstand/issues
Project-URL: Changelog, https://github.com/vdriet/waterstand/blob/main/CHANGELOG.md
Project-URL: Download, https://pypi.org/project/waterstand/
Author-email: Peter van de Riet <vdriet@gmail.com>
License-File: LICENSE
Classifier: Development Status :: 4 - Beta
Classifier: License :: OSI Approved :: MIT License
Classifier: Operating System :: OS Independent
Classifier: Programming Language :: Python :: 3
Requires-Python: >=3.11
Requires-Dist: matplotlib
Requires-Dist: pandas
Requires-Dist: seaborn
